validate/__init__.py
validate/schema.py
validate/validator.py
ss_validate-0.4.8.dist-info/LICENSE
ss_validate-0.4.8.dist-info/METADATA
ss_validate-0.4.8.dist-info/WHEEL
ss_validate-0.4.8.dist-info/entry_points.txt
ss_validate-0.4.8.dist-info/top_level.txt
ss_validate-0.4.8.dist-info/RECORD
