Metadata-Version: 2.1
Name: ss-validate
Version: 0.4.8
Summary: GWAS summary statistics file validator
Home-page: https://github.com/EBISPOT/gwas-sumstats-validator
Author: EBI SPOT
Author-email: gwas-info@ebi.ac.uk
License: Apache License, Version 2.0
Platform: UNKNOWN
License-File: LICENSE
Requires-Dist: pandas-schema (>=0.3.4)
Requires-Dist: tqdm (>=4.48.2)
